GCD of 2 number/gcd.v
module gcd_datapath (lt, gt, eq, clk, ldA, ldB, sel1, sel2, sel_in, data_in);
    output gt, lt, eq;
    input ldA, ldB, sel1, sel2, sel_in, clk;
    input [15:0] data_in;
    wire [15:0] bus, Aout, Bout, X, Y, Subout;

    PIPO A (Aout, clk, bus, ldA);
    PIPO B (Bout, clk, bus, ldB);

    mux M1 (bus, sel_in, Subout, data_in);
    mux M2 (X, sel1, Aout, Bout);
    mux M3 (Y, sel2, Aout, Bout);

    comp C1 (lt, gt, eq, Aout, Bout);
    sub S (Subout, X, Y);

endmodule

module mux (out, sel, in1, in2);
    output [15:0] out;
    input sel;
    input [15:0] in1, in2;
    assign out = sel ? in2 : in1;
endmodule

module comp (lt, gt, eq, in1, in2);
    output lt, gt, eq;
    input [15:0] in1, in2;
    assign lt = (in1<in2);
    assign gt = (in1>in2);
    assign eq = (in1==in2);
endmodule

module sub (out, in1, in2);
    output reg [15:0] out;
    input [15:0] in1, in2;
    always @(*)
    begin
    out<=in1-in2;
    end
endmodule

module PIPO (out, clk, in, load);
    output reg [15:0] out;
    input clk, load;
    input [15:0] in;

    always @(posedge clk ) begin
        if (load) out<=in;
    end
endmodule

module gcd_control (done, ldA, ldB, sel1, sel2, sel_in, clk, data_in, start, lt, gt, eq);
    output reg done, ldA, ldB, sel1, sel2, sel_in;
    input clk, start, lt, gt, eq;
    input [15:0] data_in;
    reg [2:0] state, next_state;

    parameter S0 = 3'b000, S1 = 3'b001, S2 = 3'b010, S3 = 3'b011, S4 = 3'b100, S5 = 3'b101;

    always @(posedge clk ) begin
        case (state)
                S0:     if (start) state <= S1;
                S1:     state <= S2;
                S2:     #2 if (eq) state <= S5;
                            else if (lt) state <= S3;
                            else if (gt) state <= S4;
                S3:     #2 if (eq) state <= S5;
                            else if (lt) state <= S3;
                            else if (gt) state <= S4;
                S4:    #2 if (eq) state <= S5;
                            else if (lt) state <= S3;
                            else if (gt) state <= S4;
                S5:         state <= S5;
                default:    state <= S0;
        endcase
        
        //state<=next_state;
    end

    always @(state)
    begin
        case (state)
            S0: begin
                    sel_in=1;
                    ldA=1;
                   // next_state=S1;
                    done=0;
                end

            S1: begin
                ldA=0; ldB=1; 
               // next_state=S2;
            end

            S2: begin
                ldB=0;
                sel_in=0;
                if (eq) begin
                    //next_state=S5;
                end
                else if (lt) begin
                    sel1=1; sel2=0; //next_state=S3;
                    #1 ldA=0; ldB=1;
                end
                else if (gt) begin
                    sel1=0; sel2=1; //next_state=S4;
                    #1 ldA=1; ldB=0;
                end
            end

            S3: begin
                ldA=0; ldB=0; sel_in=0;
                if (eq) begin
                    //next_state=S5;
                end
                else if (lt) begin
                    sel1=1; sel2=0; //next_state=S3;
                    #1 ldA=0; ldB=1;
                end
                else if (gt) begin
                    sel1=0; sel2=1; //next_state=S4;
                    #1 ldA=1; ldB=0;
                end
            end

            S4: begin
                ldA=0; ldB=0; sel_in=0;
                if (eq) begin
                   // next_state=S5;
                end
                else if (lt) begin
                    sel1=1; sel2=0; //next_state=S3;
                    #1 ldA=0; ldB=1;
                end
                else if (gt) begin
                    sel1=0; sel2=1; //next_state=S4;
                    #1 ldA=1; ldB=0;
                end
            end
            S5: begin
                
                ldA=0; ldB=0;
                done=1;
                // next_state=S5;
            end

            default: begin
                // next_state=S0;
                ldA=0; ldB=0;
                
            end
        endcase
    end
endmodule

GCD of 2 number/gcd_test.v
module gcd_testbench ();
    reg [15:0] data_in;
    reg clk, start;
    wire done;
    reg [15:0] A, B ;

    gcd_datapath DP (lt, gt, eq, clk, ldA, ldB, sel1, sel2, sel_in, data_in);
    gcd_control  CN (done, ldA, ldB, sel1, sel2, sel_in, clk, data_in, start, lt, gt, eq);

    initial begin
        clk=1'b0;
        #3 start = 1'b1;
        #1000 $finish;
    end

    always #5 clk=~clk;

    initial begin
        #12 data_in=143;
        #10 data_in=78;
    end

    initial begin
        $dumpfile("gcd.vcd");
        $dumpvars (0,gcd_testbench);
        $monitor ($time , "%d %b", DP.Aout, done);
    end
endmodule

GCD of 2 number/gcd.vcd
$date
	Mon Jul 17 03:09:18 2023
$end
$version
	Icarus Verilog
$end
$timescale
	1s
$end
$scope module gcd_testbench $end
$var wire 1 ! sel_in $end
$var wire 1 " sel2 $end
$var wire 1 # sel1 $end
$var wire 1 $ lt $end
$var wire 1 % ldB $end
$var wire 1 & ldA $end
$var wire 1 ' gt $end
$var wire 1 ( eq $end
$var wire 1 ) done $end
$var reg 1 * clk $end
$var reg 16 + data_in [15:0] $end
$var reg 1 , start $end
$scope module CN $end
$var wire 1 * clk $end
$var wire 16 - data_in [15:0] $end
$var wire 1 , start $end
$var wire 1 $ lt $end
$var wire 1 ' gt $end
$var wire 1 ( eq $end
$var parameter 3 . S0 $end
$var parameter 3 / S1 $end
$var parameter 3 0 S2 $end
$var parameter 3 1 S3 $end
$var parameter 3 2 S4 $end
$var parameter 3 3 S5 $end
$var reg 1 ) done $end
$var reg 1 & ldA $end
$var reg 1 % ldB $end
$var reg 1 # sel1 $end
$var reg 1 " sel2 $end
$var reg 1 ! sel_in $end
$var reg 3 4 state [2:0] $end
$upscope $end
$scope module DP $end
$var wire 1 * clk $end
$var wire 16 5 data_in [15:0] $end
$var wire 1 & ldA $end
$var wire 1 % ldB $end
$var wire 1 # sel1 $end
$var wire 1 " sel2 $end
$var wire 1 ! sel_in $end
$var wire 1 $ lt $end
$var wire 1 ' gt $end
$var wire 1 ( eq $end
$var wire 16 6 bus [15:0] $end
$var wire 16 7 Y [15:0] $end
$var wire 16 8 X [15:0] $end
$var wire 16 9 Subout [15:0] $end
$var wire 16 : Bout [15:0] $end
$var wire 16 ; Aout [15:0] $end
$scope module A $end
$var wire 1 * clk $end
$var wire 1 & load $end
$var wire 16 < in [15:0] $end
$var reg 16 = out [15:0] $end
$upscope $end
$scope module B $end
$var wire 1 * clk $end
$var wire 1 % load $end
$var wire 16 > in [15:0] $end
$var reg 16 ? out [15:0] $end
$upscope $end
$scope module C1 $end
$var wire 16 @ in1 [15:0] $end
$var wire 16 A in2 [15:0] $end
$var wire 1 $ lt $end
$var wire 1 ' gt $end
$var wire 1 ( eq $end
$upscope $end
$scope module M1 $end
$var wire 16 B in2 [15:0] $end
$var wire 1 ! sel $end
$var wire 16 C out [15:0] $end
$var wire 16 D in1 [15:0] $end
$upscope $end
$scope module M2 $end
$var wire 16 E in1 [15:0] $end
$var wire 16 F in2 [15:0] $end
$var wire 1 # sel $end
$var wire 16 G out [15:0] $end
$upscope $end
$scope module M3 $end
$var wire 16 H in1 [15:0] $end
$var wire 16 I in2 [15:0] $end
$var wire 1 " sel $end
$var wire 16 J out [15:0] $end
$upscope $end
$scope module S $end
$var wire 16 K in1 [15:0] $end
$var wire 16 L in2 [15:0] $end
$var reg 16 M out [15:0] $end
$upscope $end
$upscope $end
$upscope $end
$enddefinitions $end
$comment Show the parameter values. $end
$dumpall
b101 3
b100 2
b11 1
b10 0
b1 /
b0 .
$end
#0
$dumpvars
bx M
bx L
bx K
bx J
bx I
bx H
bx G
bx F
bx E
bx D
bx C
bx B
bx A
bx @
bx ?
bx >
bx =
bx <
bx ;
bx :
bx 9
bx 8
bx 7
bx 6
bx 5
bx 4
bx -
x,
bx +
0*
x)
x(
x'
x&
x%
x$
x#
x"
x!
$end
#3
1,
#5
0)
1&
1!
b0 4
1*
#10
0*
#12
b10001111 6
b10001111 <
b10001111 >
b10001111 C
b10001111 +
b10001111 -
b10001111 5
b10001111 B
#15
1%
0&
b1 4
b10001111 ;
b10001111 =
b10001111 @
b10001111 E
b10001111 H
1*
#20
0*
#22
b1001110 6
b1001110 <
b1001110 >
b1001110 C
b1001110 +
b1001110 -
b1001110 5
b1001110 B
#25
b1000001 9
b1000001 D
b1000001 M
b1000001 6
b1000001 <
b1000001 >
b1000001 C
b10001111 8
b10001111 G
b10001111 K
b1001110 7
b1001110 J
b1001110 L
1"
0#
0!
0%
0$
1'
0(
b1001110 :
b1001110 ?
b1001110 A
b1001110 F
b1001110 I
b10 4
1*
#26
1&
#30
0*
#35
b1111111111110011 6
b1111111111110011 <
b1111111111110011 >
b1111111111110011 C
b1111111111110011 9
b1111111111110011 D
b1111111111110011 M
b1000001 8
b1000001 G
b1000001 K
1$
0'
b1000001 ;
b1000001 =
b1000001 @
b1000001 E
b1000001 H
1*
#37
b1101 6
b1101 <
b1101 >
b1101 C
b1101 9
b1101 D
b1101 M
b1000001 7
b1000001 J
b1000001 L
b1001110 8
b1001110 G
b1001110 K
0"
1#
0&
b11 4
#38
1%
#40
0*
#45
b1111111111001100 6
b1111111111001100 <
b1111111111001100 >
b1111111111001100 C
b1111111111001100 9
b1111111111001100 D
b1111111111001100 M
b1101 8
b1101 G
b1101 K
0$
1'
b1101 :
b1101 ?
b1101 A
b1101 F
b1101 I
1*
#47
b110100 6
b110100 <
b110100 >
b110100 C
b110100 9
b110100 D
b110100 M
b1101 7
b1101 J
b1101 L
b1000001 8
b1000001 G
b1000001 K
1"
0#
0%
b100 4
#48
1&
#50
0*
#55
b100111 6
b100111 <
b100111 >
b100111 C
b100111 9
b100111 D
b100111 M
b110100 8
b110100 G
b110100 K
b110100 ;
b110100 =
b110100 @
b110100 E
b110100 H
1*
#60
0*
#65
b11010 6
b11010 <
b11010 >
b11010 C
b11010 9
b11010 D
b11010 M
b100111 8
b100111 G
b100111 K
b100111 ;
b100111 =
b100111 @
b100111 E
b100111 H
1*
#70
0*
#75
b1101 6
b1101 <
b1101 >
b1101 C
b1101 9
b1101 D
b1101 M
b11010 8
b11010 G
b11010 K
b11010 ;
b11010 =
b11010 @
b11010 E
b11010 H
1*
#80
0*
#85
b0 6
b0 <
b0 >
b0 C
b0 9
b0 D
b0 M
b1101 8
b1101 G
b1101 K
0'
1(
b1101 ;
b1101 =
b1101 @
b1101 E
b1101 H
1*
#87
1)
0&
b101 4
