Multiplication by repeated addition/mul16.v
//datapath

module mul_datapath ( ldA, ldP, clrP, data_in, ldB, decB, eqz, clk);
    output eqz;
    input [15:0] data_in;
    input ldA, ldB, ldP, clk, clrP, decB;
    wire [15:0] X, Y, Z, Bout;

    PIPO1 A (X, data_in, ldA, clk);
    PIPO2 P (Y, Z, ldP, clk, clrP);
    counter B (Bout, data_in, ldB, decB, clk);
    adder add (Z, X, Y);
    equal eq (eqz, Bout); 
endmodule

module PIPO1(out, in, load, clk);
    output reg [15:0] out;
    input [15:0] in;
    input load, clk;
    always @(posedge clk ) begin
        if(load) out<=in;
    end
endmodule

module PIPO2(out, in, load, clk, clear);
    output reg [15:0] out;
    input [15:0] in;
    input load, clk, clear;
    always @(posedge clk ) begin
        if(clear) out<= 16'b0;
        else if(load) out<=in;
    end
endmodule

module adder(out, in1, in2);
    output reg [15:0] out;
    input [15:0] in1, in2;
    always @(*)
    begin
        out=in1+in2;
    end
endmodule

module counter(out, in, load, dec, clk);
    output reg [15:0] out;
    input [15:0] in;
    input clk, dec, load;
    always @(posedge clk )
        if(load) out<=in;
        else if(dec) out<=out-1;
    
endmodule

module equal(out, in);
    output out;
    input [15:0] in;
    assign out=(in==0);
endmodule


//control path
module mul_controlpath (ldA, ldB, ldP, clrP, decB, done, start, eqz, clk);
    output reg ldA, ldB, ldP, clrP, decB, done;
    input eqz, clk, start;
    reg [2:0] state;
    parameter S0=3'b000, S1=3'b001, S2=3'b010, S3=3'b011, S4=3'b100;

    always @(posedge clk ) 
    begin
        case (state)
            S0: if(start) state<=S1;
            S1: state<=S2;
            S2: state<=S3;
            S3: #2 if(eqz) state<=S4;
            S4: state<=S4;
            default: state<=S0;
        endcase
    end

    always @(state)
    begin
        case (state)
            S0: begin
                   #1 ldA=0; ldB=0; ldP=0; clrP=0; decB=0;done=0;
                end
            S1: begin
               #1 ldA=1;
            end
            S2: begin
                #1 ldA=0; ldB=1; clrP=1; 
            end
            S3: begin
                #1 ldB=0; ldP=1; clrP=0;  decB=1;
            end
            S4: begin
                #1 done=1; ldB=0; ldP=0; decB=0;
            end
            default: begin
                   #1 ldA=0; ldB=0; ldP=0; clrP=0; decB=0;
                end
        endcase
    end
endmodule

Multiplication by repeated addition/mul16test.v
module mul16_test ();
    reg [15:0] data_in;
    reg clk, start;

    wire done;
    mul_datapath DP(ldA, ldP, clrP, data_in, ldB, decB, eqz, clk);
    mul_controlpath CN (ldA, ldB, ldP, clrP, decB, done, start, eqz, clk);

    initial begin
        clk=1'b0;
        #3 start=1'b1;
        #500 $finish;
    end
    always #5 clk= ~clk;
    initial begin
        #17 data_in=17;
        #10 data_in=5;
    end
    initial begin
        $monitor ($time, "%d %b", DP.Y, done);
        $dumpfile("mul.vcd");
        $dumpvars(0, mul16_test);
    end
    
endmodule

Multiplication by repeated addition/mul.vcd
$date
	Sun Jul 16 03:08:09 2023
$end
$version
	Icarus Verilog
$end
$timescale
	1s
$end
$scope module mul16_test $end
$var wire 1 ! ldP $end
$var wire 1 " ldB $end
$var wire 1 # ldA $end
$var wire 1 $ eqz $end
$var wire 1 % done $end
$var wire 1 & decB $end
$var wire 1 ' clrP $end
$var reg 1 ( clk $end
$var reg 16 ) data_in [15:0] $end
$var reg 1 * start $end
$scope module CN $end
$var wire 1 ( clk $end
$var wire 1 * start $end
$var wire 1 $ eqz $end
$var parameter 3 + S0 $end
$var parameter 3 , S1 $end
$var parameter 3 - S2 $end
$var parameter 3 . S3 $end
$var parameter 3 / S4 $end
$var reg 1 ' clrP $end
$var reg 1 & decB $end
$var reg 1 % done $end
$var reg 1 # ldA $end
$var reg 1 " ldB $end
$var reg 1 ! ldP $end
$var reg 3 0 state [2:0] $end
$upscope $end
$scope module DP $end
$var wire 1 ( clk $end
$var wire 1 ' clrP $end
$var wire 16 1 data_in [15:0] $end
$var wire 1 & decB $end
$var wire 1 # ldA $end
$var wire 1 " ldB $end
$var wire 1 ! ldP $end
$var wire 1 $ eqz $end
$var wire 16 2 Z [15:0] $end
$var wire 16 3 Y [15:0] $end
$var wire 16 4 X [15:0] $end
$var wire 16 5 Bout [15:0] $end
$scope module A $end
$var wire 1 ( clk $end
$var wire 16 6 in [15:0] $end
$var wire 1 # load $end
$var reg 16 7 out [15:0] $end
$upscope $end
$scope module B $end
$var wire 1 ( clk $end
$var wire 1 & dec $end
$var wire 16 8 in [15:0] $end
$var wire 1 " load $end
$var reg 16 9 out [15:0] $end
$upscope $end
$scope module P $end
$var wire 1 ' clear $end
$var wire 1 ( clk $end
$var wire 1 ! load $end
$var wire 16 : in [15:0] $end
$var reg 16 ; out [15:0] $end
$upscope $end
$scope module add $end
$var wire 16 < in1 [15:0] $end
$var wire 16 = in2 [15:0] $end
$var reg 16 > out [15:0] $end
$upscope $end
$scope module eq $end
$var wire 16 ? in [15:0] $end
$var wire 1 $ out $end
$upscope $end
$upscope $end
$upscope $end
$enddefinitions $end
$comment Show the parameter values. $end
$dumpall
b100 /
b11 .
b10 -
b1 ,
b0 +
$end
#0
$dumpvars
bx ?
bx >
bx =
bx <
bx ;
bx :
bx 9
bx 8
bx 7
bx 6
bx 5
bx 4
bx 3
bx 2
bx 1
bx 0
x*
bx )
0(
x'
x&
x%
x$
x#
x"
x!
$end
#3
1*
#5
b0 0
1(
#6
0%
0&
0'
0!
0"
0#
#10
0(
#15
b1 0
1(
#16
1#
#17
b10001 )
b10001 1
b10001 6
b10001 8
#20
0(
#25
b10001 4
b10001 7
b10001 <
b10 0
1(
#26
1'
1"
0#
#27
b101 )
b101 1
b101 6
b101 8
#30
0(
#35
b10001 2
b10001 :
b10001 >
b11 0
0$
b101 5
b101 9
b101 ?
b0 3
b0 ;
b0 =
1(
#36
1&
0'
1!
0"
#40
0(
#45
b100010 2
b100010 :
b100010 >
b10001 3
b10001 ;
b10001 =
b100 5
b100 9
b100 ?
1(
#50
0(
#55
b110011 2
b110011 :
b110011 >
b11 5
b11 9
b11 ?
b100010 3
b100010 ;
b100010 =
1(
#60
0(
#65
b1000100 2
b1000100 :
b1000100 >
b110011 3
b110011 ;
b110011 =
b10 5
b10 9
b10 ?
1(
#70
0(
#75
b1010101 2
b1010101 :
b1010101 >
b1 5
b1 9
b1 ?
b1000100 3
b1000100 ;
b1000100 =
1(
#80
0(
#85
b1100110 2
b1100110 :
b1100110 >
b1010101 3
b1010101 ;
b1010101 =
1$
b0 5
b0 9
b0 ?
1(
#87
b100 0
#88
0&
0!
1%
